betterwindow/__init__.py
betterwindow/core.py
betterwindow_ak251452-0.1.0.dist-info/METADATA
betterwindow_ak251452-0.1.0.dist-info/WHEEL
betterwindow_ak251452-0.1.0.dist-info/top_level.txt
betterwindow_ak251452-0.1.0.dist-info/RECORD
