Metadata-Version: 2.4
Name: betterwindow-ak251452
Version: 0.1.0
Summary: Biblioteka do tworzenia niestandardowych okien tkinter z własnym paskiem tytułu i przyciskami.
Author-email: Andrzej Koprowski <andrzej.koprowski007@gmail.com>
Project-URL: Homepage, https://github.com/AndrzejKoprowski251452/BetterWindow
Project-URL: Repository, https://github.com/AndrzejKoprowski251452/BetterWindow
Project-URL: Issues, https://github.com/AndrzejKoprowski251452/BetterWindow/issues
Keywords: tkinter,gui,window,custom,ui
Classifier: Development Status :: 3 - Alpha
Classifier: Intended Audience :: Developers
Classifier: Programming Language :: Python :: 3
Classifier: Programming Language :: Python :: 3.7
Classifier: Programming Language :: Python :: 3.8
Classifier: Programming Language :: Python :: 3.9
Classifier: Programming Language :: Python :: 3.10
Classifier: Programming Language :: Python :: 3.11
Classifier: Topic :: Software Development :: User Interfaces
Classifier: Operating System :: OS Independent
Requires-Python: >=3.7
